thoughtdb/.env.sample
thoughtdb/Collection.py
thoughtdb/Conversation.py
thoughtdb/Core.py
thoughtdb/Document.py
thoughtdb/Organization.py
thoughtdb/VectorStore.py
thoughtdb/VectorTool.py
thoughtdb/__init__.py
thoughtdb/app.sample
thoughtdb/database/readme.md
thoughtdb/migrations/00001_initial_database_design.sql
thoughtdb/migrations/00002_add_relevant_indexes.sql
thoughtdb/migrations/readme.md
thoughtdb/models_db/nomic-embed-text-v1.5.Q4_K_M.gguf
thoughtdb/models_db/readme.md
thoughtdb/readme.md
thoughtdb/routes/readme.md
thoughtdb-0.1.2.dist-info/LICENSE
thoughtdb-0.1.2.dist-info/METADATA
thoughtdb-0.1.2.dist-info/WHEEL
thoughtdb-0.1.2.dist-info/RECORD
