Metadata-Version: 2.1
Name: thoughtdb
Version: 0.1.2
Summary: ThoughtDB is a mix between relational and vector database for efficient data retrieval
License: MIT
Author: Andre van Zuydam
Author-email: andrevanzuydam@gmail.com
Requires-Python: >=3.11,<4.0
Classifier: License :: OSI Approved :: MIT License
Classifier: Programming Language :: Python :: 3
Classifier: Programming Language :: Python :: 3.11
Classifier: Programming Language :: Python :: 3.12
Requires-Dist: cleantext (>=1.1.4,<2.0.0)
Requires-Dist: llama-cpp-python (==0.2.83)
Requires-Dist: numpy (>=2.0.1,<3.0.0)
Requires-Dist: sqlite-vec (>=0.1.1,<0.2.0)
Requires-Dist: tina4-python (>=0.1.95,<0.2.0)
